winuse_cli/__init__.py
winuse_cli/cli.py
winuse-0.1.0.dist-info/METADATA
winuse-0.1.0.dist-info/WHEEL
winuse-0.1.0.dist-info/entry_points.txt
winuse-0.1.0.dist-info/top_level.txt
winuse-0.1.0.dist-info/RECORD
