Metadata-Version: 2.4
Name: winuse
Version: 0.1.0
Summary: WinUse CLI to control the WinUse Windows agent API.
Requires-Python: >=3.9
Requires-Dist: requests==2.32.5
